[{"id":1622548800,"dateTime":"2021-06-01T12:00:00.000Z","treatmentName":"scrub","userId":100},{"id":1622556000,"dateTime":"2021-06-01T14:00:00.000Z","treatmentName":"massage"},{"id":1622628000,"dateTime":"2021-06-02T10:00:00.000Z","treatmentName":"facial","userId":100},{"id":1622646000,"dateTime":"2021-06-02T15:00:00.000Z","treatmentName":"scrub"},{"id":1622707200,"dateTime":"2021-06-03T08:00:00.000Z","treatmentName":"scrub"},{"id":1622721600,"dateTime":"2021-06-03T12:00:00.000Z","treatmentName":"scrub"},{"id":1622808000,"dateTime":"2021-06-04T12:00:00.000Z","treatmentName":"massage"},{"id":1622815200,"dateTime":"2021-06-04T14:00:00.000Z","treatmentName":"massage","userId":100},{"id":1623056400,"dateTime":"2021-06-07T09:00:00.000Z","treatmentName":"massage","userId":100},{"id":1623070800,"dateTime":"2021-06-07T13:00:00.000Z","treatmentName":"facial","userId":100},{"id":1623153600,"dateTime":"2021-06-08T12:00:00.000Z","treatmentName":"scrub","userId":100},{"id":1623160800,"dateTime":"2021-06-08T14:00:00.000Z","treatmentName":"massage","userId":100},{"id":1623232800,"dateTime":"2021-06-09T10:00:00.000Z","treatmentName":"facial"},{"id":1623250800,"dateTime":"2021-06-09T15:00:00.000Z","treatmentName":"scrub","userId":100},{"id":1623312000,"dateTime":"2021-06-10T08:00:00.000Z","treatmentName":"scrub"},{"id":1623326400,"dateTime":"2021-06-10T12:00:00.000Z","treatmentName":"scrub"},{"id":1623412800,"dateTime":"2021-06-11T12:00:00.000Z","treatmentName":"massage"},{"id":1623420000,"dateTime":"2021-06-11T14:00:00.000Z","treatmentName":"massage"},{"id":1623661200,"dateTime":"2021-06-14T09:00:00.000Z","treatmentName":"massage"},{"id":1623675600,"dateTime":"2021-06-14T13:00:00.000Z","treatmentName":"facial"},{"id":1623758400,"dateTime":"2021-06-15T12:00:00.000Z","treatmentName":"scrub"},{"id":1623765600,"dateTime":"2021-06-15T14:00:00.000Z","treatmentName":"massage"},{"id":1623837600,"dateTime":"2021-06-16T10:00:00.000Z","treatmentName":"facial","userId":100},{"id":1623855600,"dateTime":"2021-06-16T15:00:00.000Z","treatmentName":"scrub","userId":100},{"id":1623916800,"dateTime":"2021-06-17T08:00:00.000Z","treatmentName":"scrub"},{"id":1623931200,"dateTime":"2021-06-17T12:00:00.000Z","treatmentName":"scrub","userId":100},{"id":1624017600,"dateTime":"2021-06-18T12:00:00.000Z","treatmentName":"massage"},{"id":1624024800,"dateTime":"2021-06-18T14:00:00.000Z","treatmentName":"massage"},{"id":1624266000,"dateTime":"2021-06-21T09:00:00.000Z","treatmentName":"massage"},{"id":1624280400,"dateTime":"2021-06-21T13:00:00.000Z","treatmentName":"facial"},{"id":1624363200,"dateTime":"2021-06-22T12:00:00.000Z","treatmentName":"scrub"},{"id":1624370400,"dateTime":"2021-06-22T14:00:00.000Z","treatmentName":"massage"},{"id":1624442400,"dateTime":"2021-06-23T10:00:00.000Z","treatmentName":"facial"},{"id":1624460400,"dateTime":"2021-06-23T15:00:00.000Z","treatmentName":"scrub","userId":100},{"id":1624521600,"dateTime":"2021-06-24T08:00:00.000Z","treatmentName":"scrub","userId":100},{"id":1624536000,"dateTime":"2021-06-24T12:00:00.000Z","treatmentName":"scrub"},{"id":1624622400,"dateTime":"2021-06-25T12:00:00.000Z","treatmentName":"massage","userId":100},{"id":1624629600,"dateTime":"2021-06-25T14:00:00.000Z","treatmentName":"massage","userId":100},{"id":1624870800,"dateTime":"2021-06-28T09:00:00.000Z","treatmentName":"massage"},{"id":1624885200,"dateTime":"2021-06-28T13:00:00.000Z","treatmentName":"facial","userId":100},{"id":1624968000,"dateTime":"2021-06-29T12:00:00.000Z","treatmentName":"scrub"},{"id":1624975200,"dateTime":"2021-06-29T14:00:00.000Z","treatmentName":"massage"},{"id":1625047200,"dateTime":"2021-06-30T10:00:00.000Z","treatmentName":"facial","userId":100},{"id":1625065200,"dateTime":"2021-06-30T15:00:00.000Z","treatmentName":"scrub"},{"id":1625126400,"dateTime":"2021-07-01T08:00:00.000Z","treatmentName":"scrub"},{"id":1625140800,"dateTime":"2021-07-01T12:00:00.000Z","treatmentName":"scrub"},{"id":1625227200,"dateTime":"2021-07-02T12:00:00.000Z","treatmentName":"massage","userId":100},{"id":1625234400,"dateTime":"2021-07-02T14:00:00.000Z","treatmentName":"massage","userId":100},{"id":1625475600,"dateTime":"2021-07-05T09:00:00.000Z","treatmentName":"massage"},{"id":1625490000,"dateTime":"2021-07-05T13:00:00.000Z","treatmentName":"facial"},{"id":1625572800,"dateTime":"2021-07-06T12:00:00.000Z","treatmentName":"scrub"},{"id":1625580000,"dateTime":"2021-07-06T14:00:00.000Z","treatmentName":"massage","userId":100},{"id":1625652000,"dateTime":"2021-07-07T10:00:00.000Z","treatmentName":"facial"},{"id":1625670000,"dateTime":"2021-07-07T15:00:00.000Z","treatmentName":"scrub","userId":100},{"id":1625731200,"dateTime":"2021-07-08T08:00:00.000Z","treatmentName":"scrub"},{"id":1625745600,"dateTime":"2021-07-08T12:00:00.000Z","treatmentName":"scrub"},{"id":1625832000,"dateTime":"2021-07-09T12:00:00.000Z","treatmentName":"massage"},{"id":1625839200,"dateTime":"2021-07-09T14:00:00.000Z","treatmentName":"massage"},{"id":1626080400,"dateTime":"2021-07-12T09:00:00.000Z","treatmentName":"massage"},{"id":1626094800,"dateTime":"2021-07-12T13:00:00.000Z","treatmentName":"facial"},{"id":1626177600,"dateTime":"2021-07-13T12:00:00.000Z","treatmentName":"scrub","userId":100},{"id":1626184800,"dateTime":"2021-07-13T14:00:00.000Z","treatmentName":"massage","userId":100},{"id":1626256800,"dateTime":"2021-07-14T10:00:00.000Z","treatmentName":"facial","userId":100},{"id":1626274800,"dateTime":"2021-07-14T15:00:00.000Z","treatmentName":"scrub"},{"id":1626336000,"dateTime":"2021-07-15T08:00:00.000Z","treatmentName":"scrub","userId":100},{"id":1626350400,"dateTime":"2021-07-15T12:00:00.000Z","treatmentName":"scrub","userId":100},{"id":1626436800,"dateTime":"2021-07-16T12:00:00.000Z","treatmentName":"massage","userId":100},{"id":1626444000,"dateTime":"2021-07-16T14:00:00.000Z","treatmentName":"massage","userId":100},{"id":1626685200,"dateTime":"2021-07-19T09:00:00.000Z","treatmentName":"massage","userId":100},{"id":1626699600,"dateTime":"2021-07-19T13:00:00.000Z","treatmentName":"facial"},{"id":1626782400,"dateTime":"2021-07-20T12:00:00.000Z","treatmentName":"scrub"},{"id":1626789600,"dateTime":"2021-07-20T14:00:00.000Z","treatmentName":"massage","userId":100},{"id":1626861600,"dateTime":"2021-07-21T10:00:00.000Z","treatmentName":"facial","userId":100},{"id":1626879600,"dateTime":"2021-07-21T15:00:00.000Z","treatmentName":"scrub"},{"id":1626940800,"dateTime":"2021-07-22T08:00:00.000Z","treatmentName":"scrub","userId":100},{"id":1626955200,"dateTime":"2021-07-22T12:00:00.000Z","treatmentName":"scrub","userId":100},{"id":1627041600,"dateTime":"2021-07-23T12:00:00.000Z","treatmentName":"massage"},{"id":1627048800,"dateTime":"2021-07-23T14:00:00.000Z","treatmentName":"massage","userId":100},{"id":1627290000,"dateTime":"2021-07-26T09:00:00.000Z","treatmentName":"massage","userId":100},{"id":1627304400,"dateTime":"2021-07-26T13:00:00.000Z","treatmentName":"facial","userId":100},{"id":1627387200,"dateTime":"2021-07-27T12:00:00.000Z","treatmentName":"scrub","userId":100},{"id":1627394400,"dateTime":"2021-07-27T14:00:00.000Z","treatmentName":"massage","userId":100},{"id":1627466400,"dateTime":"2021-07-28T10:00:00.000Z","treatmentName":"facial"},{"id":1627484400,"dateTime":"2021-07-28T15:00:00.000Z","treatmentName":"scrub"},{"id":1627545600,"dateTime":"2021-07-29T08:00:00.000Z","treatmentName":"scrub","userId":100},{"id":1627560000,"dateTime":"2021-07-29T12:00:00.000Z","treatmentName":"scrub"},{"id":1627646400,"dateTime":"2021-07-30T12:00:00.000Z","treatmentName":"massage"},{"id":1627653600,"dateTime":"2021-07-30T14:00:00.000Z","treatmentName":"massage"},{"id":1627894800,"dateTime":"2021-08-02T09:00:00.000Z","treatmentName":"massage","userId":100},{"id":1627909200,"dateTime":"2021-08-02T13:00:00.000Z","treatmentName":"facial","userId":100},{"id":1627992000,"dateTime":"2021-08-03T12:00:00.000Z","treatmentName":"scrub"},{"id":1627999200,"dateTime":"2021-08-03T14:00:00.000Z","treatmentName":"massage","userId":100},{"id":1628071200,"dateTime":"2021-08-04T10:00:00.000Z","treatmentName":"facial"},{"id":1628089200,"dateTime":"2021-08-04T15:00:00.000Z","treatmentName":"scrub"},{"id":1628150400,"dateTime":"2021-08-05T08:00:00.000Z","treatmentName":"scrub"},{"id":1628164800,"dateTime":"2021-08-05T12:00:00.000Z","treatmentName":"scrub"},{"id":1628251200,"dateTime":"2021-08-06T12:00:00.000Z","treatmentName":"massage","userId":100},{"id":1628258400,"dateTime":"2021-08-06T14:00:00.000Z","treatmentName":"massage"},{"id":1628499600,"dateTime":"2021-08-09T09:00:00.000Z","treatmentName":"massage"},{"id":1628514000,"dateTime":"2021-08-09T13:00:00.000Z","treatmentName":"facial","userId":100},{"id":1628596800,"dateTime":"2021-08-10T12:00:00.000Z","treatmentName":"scrub","userId":100},{"id":1628604000,"dateTime":"2021-08-10T14:00:00.000Z","treatmentName":"massage"},{"id":1628676000,"dateTime":"2021-08-11T10:00:00.000Z","treatmentName":"facial","userId":100},{"id":1628694000,"dateTime":"2021-08-11T15:00:00.000Z","treatmentName":"scrub"},{"id":1628755200,"dateTime":"2021-08-12T08:00:00.000Z","treatmentName":"scrub"},{"id":1628769600,"dateTime":"2021-08-12T12:00:00.000Z","treatmentName":"scrub","userId":100},{"id":1628856000,"dateTime":"2021-08-13T12:00:00.000Z","treatmentName":"massage"},{"id":1628863200,"dateTime":"2021-08-13T14:00:00.000Z","treatmentName":"massage","userId":100},{"id":1629104400,"dateTime":"2021-08-16T09:00:00.000Z","treatmentName":"massage"},{"id":1629118800,"dateTime":"2021-08-16T13:00:00.000Z","treatmentName":"facial","userId":100},{"id":1629201600,"dateTime":"2021-08-17T12:00:00.000Z","treatmentName":"scrub","userId":100},{"id":1629208800,"dateTime":"2021-08-17T14:00:00.000Z","treatmentName":"massage","userId":100},{"id":1629280800,"dateTime":"2021-08-18T10:00:00.000Z","treatmentName":"facial"},{"id":1629298800,"dateTime":"2021-08-18T15:00:00.000Z","treatmentName":"scrub"},{"id":1629360000,"dateTime":"2021-08-19T08:00:00.000Z","treatmentName":"scrub"},{"id":1629374400,"dateTime":"2021-08-19T12:00:00.000Z","treatmentName":"scrub","userId":100},{"id":1629460800,"dateTime":"2021-08-20T12:00:00.000Z","treatmentName":"massage"},{"id":1629468000,"dateTime":"2021-08-20T14:00:00.000Z","treatmentName":"massage"},{"id":1629709200,"dateTime":"2021-08-23T09:00:00.000Z","treatmentName":"massage","userId":100},{"id":1629723600,"dateTime":"2021-08-23T13:00:00.000Z","treatmentName":"facial"},{"id":1629806400,"dateTime":"2021-08-24T12:00:00.000Z","treatmentName":"scrub"},{"id":1629813600,"dateTime":"2021-08-24T14:00:00.000Z","treatmentName":"massage"},{"id":1629885600,"dateTime":"2021-08-25T10:00:00.000Z","treatmentName":"facial","userId":100},{"id":1629903600,"dateTime":"2021-08-25T15:00:00.000Z","treatmentName":"scrub","userId":100},{"id":1629964800,"dateTime":"2021-08-26T08:00:00.000Z","treatmentName":"scrub","userId":100},{"id":1629979200,"dateTime":"2021-08-26T12:00:00.000Z","treatmentName":"scrub","userId":100},{"id":1630065600,"dateTime":"2021-08-27T12:00:00.000Z","treatmentName":"massage"},{"id":1630072800,"dateTime":"2021-08-27T14:00:00.000Z","treatmentName":"massage","userId":100},{"id":1630314000,"dateTime":"2021-08-30T09:00:00.000Z","treatmentName":"massage","userId":100},{"id":1630328400,"dateTime":"2021-08-30T13:00:00.000Z","treatmentName":"facial"},{"id":1630411200,"dateTime":"2021-08-31T12:00:00.000Z","treatmentName":"scrub","userId":100},{"id":1630418400,"dateTime":"2021-08-31T14:00:00.000Z","treatmentName":"massage"}]